setup.py
MySerializerForJsonAndXML.egg-info/PKG-INFO
MySerializerForJsonAndXML.egg-info/SOURCES.txt
MySerializerForJsonAndXML.egg-info/dependency_links.txt
MySerializerForJsonAndXML.egg-info/requires.txt
MySerializerForJsonAndXML.egg-info/top_level.txt
Serializators/CLI.py
Serializators/Creator.py
Serializators/JSON.py
Serializators/XML.py