Metadata-Version: 2.1
Name: MySerializerForJsonAndXML
Version: 0.1.0
Summary: Demo library
Author: Teplyakov Arseny
Author-email: teplyakovarseni@mail.ru
Classifier: Intended Audience :: Developers
Classifier: Programming Language :: Python :: 3.10
Classifier: Operating System :: OS Independent
